turntable.pyi
turntable.cpython-312-x86_64-linux-gnu.so
turntable.build/.gitignore
turntable_cli-0.4.11.dist-info/top_level.txt
turntable_cli-0.4.11.dist-info/RECORD
turntable_cli-0.4.11.dist-info/LICENSE
turntable_cli-0.4.11.dist-info/entry_points.txt
turntable_cli-0.4.11.dist-info/METADATA
turntable_cli-0.4.11.dist-info/WHEEL
